<customUI xmlns="http://schemas.microsoft.com/office/2009/07/customui">
    <ribbon>
        <tabs>
            <tab idMso="TabHome" visible="false" />
            <tab id="customTab" insertAfterMso="TabView" label="Tab">
                <group id="customGroup" label="Group">
                    <button
                        id="customButton"
                        label="Button"
                    <!-- highlight-next-line -->
                    imageMso="AddFolderToFavorites"
                    size="large"
                    onAction="OnButtonClicked" />
                </group>
            </tab>
        </tabs>
    </ribbon>
</customUI>